zope.tal-5.1.1-py3.12-nspkg.pth
zope/tal/__init__.py
zope/tal/driver.py
zope/tal/dummyengine.py
zope/tal/htmltalparser.py
zope/tal/interfaces.py
zope/tal/runtest.py
zope/tal/taldefs.py
zope/tal/talgenerator.py
zope/tal/talgettext.py
zope/tal/talinterpreter.py
zope/tal/talparser.py
zope/tal/timer.py
zope/tal/translationcontext.py
zope/tal/xmlparser.py
zope/tal/benchmark/__init__.py
zope/tal/benchmark/dtml01.html
zope/tal/benchmark/dtml02.html
zope/tal/benchmark/dtml03.html
zope/tal/benchmark/dtml04.html
zope/tal/benchmark/dtml05.html
zope/tal/benchmark/dtml06.html
zope/tal/benchmark/dtml07.html
zope/tal/benchmark/dtml08.html
zope/tal/benchmark/dtml09.html
zope/tal/benchmark/dtml10.html
zope/tal/benchmark/dtml11.html
zope/tal/benchmark/dtml12.html
zope/tal/benchmark/tal01.html
zope/tal/benchmark/tal02.html
zope/tal/benchmark/tal03.html
zope/tal/benchmark/tal04.html
zope/tal/benchmark/tal05.html
zope/tal/benchmark/tal06.html
zope/tal/benchmark/tal07.html
zope/tal/benchmark/tal08.html
zope/tal/benchmark/tal09.html
zope/tal/benchmark/tal10.html
zope/tal/benchmark/tal11.html
zope/tal/benchmark/tal12.html
zope/tal/tests/__init__.py
zope/tal/tests/markbench.py
zope/tal/tests/run.py
zope/tal/tests/test_files.py
zope/tal/tests/test_htmltalparser.py
zope/tal/tests/test_sourcepos.py
zope/tal/tests/test_talgettext.py
zope/tal/tests/test_talinterpreter.py
zope/tal/tests/test_talparser.py
zope/tal/tests/test_xmlparser.py
zope/tal/tests/utils.py
zope/tal/tests/input/__init__.py
zope/tal/tests/input/acme_template.pt
zope/tal/tests/input/document_list.pt
zope/tal/tests/input/pnome_template.pt
zope/tal/tests/input/test01.html
zope/tal/tests/input/test01.xml
zope/tal/tests/input/test02.html
zope/tal/tests/input/test02.xml
zope/tal/tests/input/test03.html
zope/tal/tests/input/test03.xml
zope/tal/tests/input/test04.html
zope/tal/tests/input/test04.xml
zope/tal/tests/input/test05.html
zope/tal/tests/input/test05.xml
zope/tal/tests/input/test06.html
zope/tal/tests/input/test06.xml
zope.tal-5.1.1.dist-info/LICENSE.rst
zope.tal-5.1.1.dist-info/METADATA
zope.tal-5.1.1.dist-info/WHEEL
zope.tal-5.1.1.dist-info/namespace_packages.txt
zope.tal-5.1.1.dist-info/top_level.txt
zope.tal-5.1.1.dist-info/RECORD
